Metadata-Version: 2.1
Name: odoo14-addon-fetchmail_notify_error_to_sender_test
Version: 14.0.1.0.1.dev6
Summary: Test for Fetchmail Notify Error to Sender
Home-page: https://github.com/OCA/server-tools
Author: Agile Business Group,ForgeFlow,Odoo Community Association (OCA)
Author-email: support@odoo-community.org
License: AGPL-3
Classifier: Programming Language :: Python
Classifier: Framework :: Odoo
Classifier: Framework :: Odoo :: 14.0
Classifier: License :: OSI Approved :: GNU Affero General Public License v3
Requires-Python: >=3.6
Requires-Dist: odoo14-addon-fetchmail-notify-error-to-sender
Requires-Dist: odoo<14.1dev,>=14.0a
